{
  "kind": "singleType",
  "collectionName": "homepages",
  "info": {
    "singularName": "homepage",
    "pluralName": "homepages",
    "displayName": "Domovská stránka",
    "description": ""
  },
  "options": {
    "draftAndPublish": false
  },
  "pluginOptions": {},
  "attributes": {
    "title": {
      "type": "string",
      "required": true
    },
    "images": {
      "displayName": "HomeImage",
      "type": "component",
      "repeatable": true,
      "component": "homepage.home-image"
    }
  }
}
