{
  "name": "Admin",
  "code": "strapi-editor",
  "description": "Admin může editovat téměř všechen obsah na webu a vytvářet nové strapi uživatele.",
  "permissions": [
    {
      "action": "plugin::content-manager.explorer.create",
      "subject": "api::post.post",
      "properties": {
        "fields": [
          "title",
          "content",
          "files",
          "troops",
          "user_likes",
          "schedule_publish_at"
        ]
      },
      "conditions": []
    },
    {
      "action": "plugin::content-manager.explorer.delete",
      "subject": "api::post.post",
      "properties": {},
      "conditions": []
    },
    {
      "action": "plugin::content-manager.explorer.publish",
      "subject": "api::post.post",
      "properties": {},
      "conditions": []
    },
    {
      "action": "plugin::content-manager.explorer.read",
      "subject": "api::post.post",
      "properties": {
        "fields": [
          "title",
          "content",
          "files",
          "troops",
          "user_likes",
          "schedule_publish_at"
        ]
      },
      "conditions": []
    },
    {
      "action": "plugin::content-manager.explorer.update",
      "subject": "api::post.post",
      "properties": {
        "fields": [
          "title",
          "content",
          "files",
          "troops",
          "user_likes",
          "schedule_publish_at"
        ]
      },
      "conditions": []
    },
    {
      "action": "plugin::content-manager.explorer.create",
      "subject": "api::top-bar.top-bar",
      "properties": {
        "fields": [
          "content",
          "type"
        ]
      },
      "conditions": []
    },
    {
      "action": "plugin::content-manager.explorer.delete",
      "subject": "api::top-bar.top-bar",
      "properties": {},
      "conditions": []
    },
    {
      "action": "plugin::content-manager.explorer.read",
      "subject": "api::top-bar.top-bar",
      "properties": {
        "fields": [
          "content",
          "type"
        ]
      },
      "conditions": []
    },
    {
      "action": "plugin::content-manager.explorer.update",
      "subject": "api::top-bar.top-bar",
      "properties": {
        "fields": [
          "content",
          "type"
        ]
      },
      "conditions": []
    },
    {
      "action": "plugin::content-manager.explorer.read",
      "subject": "api::troop.troop",
      "properties": {
        "fields": [
          "name",
          "subscribed_users",
          "posts"
        ]
      },
      "conditions": []
    },
    {
      "action": "admin::roles.read",
      "subject": null,
      "properties": {},
      "conditions": []
    },
    {
      "action": "admin::users.create",
      "subject": null,
      "properties": {},
      "conditions": []
    },
    {
      "action": "admin::users.delete",
      "subject": null,
      "properties": {},
      "conditions": []
    },
    {
      "action": "admin::users.read",
      "subject": null,
      "properties": {},
      "conditions": []
    },
    {
      "action": "admin::users.update",
      "subject": null,
      "properties": {},
      "conditions": []
    },
    {
      "action": "plugin::content-manager.explorer.create",
      "subject": "plugin::users-permissions.user",
      "properties": {
        "fields": [
          "email",
          "resetPasswordToken",
          "confirmationToken",
          "confirmed",
          "blocked",
          "role",
          "firstName",
          "lastName",
          "subscribing_troops",
          "post_likes"
        ]
      },
      "conditions": []
    },
    {
      "action": "plugin::content-manager.explorer.delete",
      "subject": "plugin::users-permissions.user",
      "properties": {},
      "conditions": []
    },
    {
      "action": "plugin::content-manager.explorer.read",
      "subject": "plugin::users-permissions.user",
      "properties": {
        "fields": [
          "email",
          "provider",
          "password",
          "resetPasswordToken",
          "confirmationToken",
          "confirmed",
          "blocked",
          "role",
          "firstName",
          "lastName",
          "subscribing_troops",
          "post_likes"
        ]
      },
      "conditions": []
    },
    {
      "action": "plugin::content-manager.explorer.update",
      "subject": "plugin::users-permissions.user",
      "properties": {
        "fields": [
          "email",
          "resetPasswordToken",
          "confirmationToken",
          "blocked",
          "firstName",
          "lastName",
          "subscribing_troops"
        ]
      },
      "conditions": []
    },
    {
      "action": "plugin::upload.assets.copy-link",
      "subject": null,
      "properties": {},
      "conditions": []
    },
    {
      "action": "plugin::upload.assets.create",
      "subject": null,
      "properties": {},
      "conditions": []
    },
    {
      "action": "plugin::upload.assets.download",
      "subject": null,
      "properties": {},
      "conditions": []
    },
    {
      "action": "plugin::upload.assets.update",
      "subject": null,
      "properties": {},
      "conditions": []
    },
    {
      "action": "plugin::upload.read",
      "subject": null,
      "properties": {},
      "conditions": []
    }
  ]
}
