{
  "key": "plugin_content_manager_configuration_content_types::api::troop.troop",
  "value": {
    "uid": "api::troop.troop",
    "settings": {
      "bulkable": true,
      "filterable": true,
      "searchable": true,
      "pageSize": 10,
      "mainField": "name",
      "defaultSortBy": "name",
      "defaultSortOrder": "ASC"
    },
    "metadatas": {
      "id": {
        "edit": {},
        "list": {
          "label": "ID",
          "searchable": true,
          "sortable": true
        }
      },
      "name": {
        "edit": {
          "label": "Název oddílu",
          "description": "např. Skauti",
          "placeholder": "",
          "visible": true,
          "editable": true
        },
        "list": {
          "label": "Název oddílu",
          "searchable": true,
          "sortable": true
        }
      },
      "subscribed_users": {
        "edit": {
          "label": "Uživatelé odebírající příspěvky",
          "description": "",
          "placeholder": "",
          "visible": true,
          "editable": true,
          "mainField": "username"
        },
        "list": {
          "label": "Uživatelé odebírající příspěvky",
          "searchable": false,
          "sortable": false
        }
      },
      "posts": {
        "edit": {
          "label": "Příspěvky",
          "description": "",
          "placeholder": "",
          "visible": true,
          "editable": true,
          "mainField": "title"
        },
        "list": {
          "label": "Příspěvky",
          "searchable": false,
          "sortable": false
        }
      },
      "color": {
        "edit": {
          "label": "Barva",
          "description": "",
          "placeholder": "",
          "visible": true,
          "editable": true
        },
        "list": {
          "label": "color",
          "searchable": true,
          "sortable": true
        }
      },
      "createdAt": {
        "edit": {
          "label": "createdAt",
          "description": "",
          "placeholder": "",
          "visible": false,
          "editable": true
        },
        "list": {
          "label": "Vytvořeno",
          "searchable": true,
          "sortable": true
        }
      },
      "updatedAt": {
        "edit": {
          "label": "updatedAt",
          "description": "",
          "placeholder": "",
          "visible": false,
          "editable": true
        },
        "list": {
          "label": "Aktualizováno",
          "searchable": true,
          "sortable": true
        }
      }
    },
    "layouts": {
      "edit": [
        [
          {
            "name": "name",
            "size": 6
          },
          {
            "name": "color",
            "size": 6
          }
        ]
      ],
      "editRelations": [
        "subscribed_users",
        "posts"
      ],
      "list": [
        "id",
        "name",
        "createdAt",
        "subscribed_users"
      ]
    }
  },
  "type": "object",
  "environment": null,
  "tag": null
}